Orange3_Bioinformatics-4.8.4-py3.11-nspkg.pth
orangecontrib/bioinformatics/__init__.py
orangecontrib/bioinformatics/annotation/__init__.py
orangecontrib/bioinformatics/annotation/annotate_projection.py
orangecontrib/bioinformatics/annotation/annotate_samples.py
orangecontrib/bioinformatics/cluster_analysis/__init__.py
orangecontrib/bioinformatics/dicty/__init__.py
orangecontrib/bioinformatics/dicty/phenotypes.py
orangecontrib/bioinformatics/geneset/__init__.py
orangecontrib/bioinformatics/geneset/utils.py
orangecontrib/bioinformatics/geo/__init__.py
orangecontrib/bioinformatics/geo/dataset.py
orangecontrib/bioinformatics/go/__init__.py
orangecontrib/bioinformatics/go/config.py
orangecontrib/bioinformatics/kegg/__init__.py
orangecontrib/bioinformatics/kegg/api.py
orangecontrib/bioinformatics/kegg/brite.py
orangecontrib/bioinformatics/kegg/caching.py
orangecontrib/bioinformatics/kegg/conf.py
orangecontrib/bioinformatics/kegg/databases.py
orangecontrib/bioinformatics/kegg/pathway.py
orangecontrib/bioinformatics/kegg/service.py
orangecontrib/bioinformatics/kegg/types.py
orangecontrib/bioinformatics/kegg/entry/__init__.py
orangecontrib/bioinformatics/kegg/entry/fields.py
orangecontrib/bioinformatics/kegg/entry/parser.py
orangecontrib/bioinformatics/ncbi/__init__.py
orangecontrib/bioinformatics/ncbi/gene/__init__.py
orangecontrib/bioinformatics/ncbi/gene/config.py
orangecontrib/bioinformatics/ncbi/homologene/__init__.py
orangecontrib/bioinformatics/ncbi/taxonomy/__init__.py
orangecontrib/bioinformatics/ncbi/taxonomy/utils.py
orangecontrib/bioinformatics/preprocess/__init__.py
orangecontrib/bioinformatics/preprocess/normalize.py
orangecontrib/bioinformatics/resolwe/__init__.py
orangecontrib/bioinformatics/resolwe/genapi.py
orangecontrib/bioinformatics/resolwe/resapi.py
orangecontrib/bioinformatics/resolwe/utils.py
orangecontrib/bioinformatics/tests/__init__.py
orangecontrib/bioinformatics/tests/test_geneset.py
orangecontrib/bioinformatics/tests/test_geo.py
Orange3_Bioinformatics-4.8.4.dist-info/LICENSE
Orange3_Bioinformatics-4.8.4.dist-info/METADATA
Orange3_Bioinformatics-4.8.4.dist-info/WHEEL
Orange3_Bioinformatics-4.8.4.dist-info/entry_points.txt
Orange3_Bioinformatics-4.8.4.dist-info/namespace_packages.txt
Orange3_Bioinformatics-4.8.4.dist-info/top_level.txt
Orange3_Bioinformatics-4.8.4.dist-info/RECORD
